.gitignore
.gitmodules
.pre-commit-config.yaml
CMakeLists.txt
LICENSE
README.md
noxfile.py
pyproject.toml
setup.py
.github/dependabot.yml
.github/workflows/conda.yml
.github/workflows/pip.yml
.github/workflows/wheels.yml
_skbuild/linux-x86_64-3.9/cmake-install/.gitignore
_skbuild/linux-x86_64-3.9/cmake-install/.gitmodules
_skbuild/linux-x86_64-3.9/cmake-install/.pre-commit-config.yaml
_skbuild/linux-x86_64-3.9/cmake-install/CMakeLists.txt
_skbuild/linux-x86_64-3.9/cmake-install/LICENSE
_skbuild/linux-x86_64-3.9/cmake-install/README.md
_skbuild/linux-x86_64-3.9/cmake-install/noxfile.py
_skbuild/linux-x86_64-3.9/cmake-install/pyproject.toml
_skbuild/linux-x86_64-3.9/cmake-install/setup.py
_skbuild/linux-x86_64-3.9/cmake-install/.github/dependabot.yml
_skbuild/linux-x86_64-3.9/cmake-install/.github/workflows/conda.yml
_skbuild/linux-x86_64-3.9/cmake-install/.github/workflows/pip.yml
_skbuild/linux-x86_64-3.9/cmake-install/.github/workflows/wheels.yml
_skbuild/linux-x86_64-3.9/cmake-install/conda.recipe/meta.yaml
_skbuild/linux-x86_64-3.9/cmake-install/docs/Makefile
_skbuild/linux-x86_64-3.9/cmake-install/docs/conf.py
_skbuild/linux-x86_64-3.9/cmake-install/docs/index.rst
_skbuild/linux-x86_64-3.9/cmake-install/docs/make.bat
_skbuild/linux-x86_64-3.9/cmake-install/docs/python_example.rst
_skbuild/linux-x86_64-3.9/cmake-install/extern/pybind11/.appveyor.yml
_skbuild/linux-x86_64-3.9/cmake-install/extern/pybind11/.clang-format
_skbuild/linux-x86_64-3.9/cmake-install/extern/pybind11/.clang-tidy
_skbuild/linux-x86_64-3.9/cmake-install/extern/pybind11/.cmake-format.yaml
_skbuild/linux-x86_64-3.9/cmake-install/extern/pybind11/.gitignore
_skbuild/linux-x86_64-3.9/cmake-install/extern/pybind11/.pre-commit-config.yaml
_skbuild/linux-x86_64-3.9/cmake-install/extern/pybind11/.readthedocs.yml
_skbuild/linux-x86_64-3.9/cmake-install/extern/pybind11/CMakeLists.txt
_skbuild/linux-x86_64-3.9/cmake-install/extern/pybind11/LICENSE
src/fastvarints.egg-info/PKG-INFO
src/fastvarints.egg-info/SOURCES.txt
src/fastvarints.egg-info/dependency_links.txt
src/fastvarints.egg-info/not-zip-safe
src/fastvarints.egg-info/requires.txt
src/fastvarints.egg-info/top_level.txt
