Metadata-Version: 2.1
Name: fastvarints
Version: 0.0.1
Summary: Implements the elais gamma encoding for numpy arrays
Author: Jeffrey Wigger
License: MIT
Platform: UNKNOWN
Requires-Python: >=3.9
Provides-Extra: test
License-File: LICENSE
